README.md
setup.py
mandrel/__init__.py
mandrel/bootstrap.py
mandrel/exception.py
mandrel/runner.py
mandrel/util.py
mandrel.egg-info/PKG-INFO
mandrel.egg-info/SOURCES.txt
mandrel.egg-info/dependency_links.txt
mandrel.egg-info/entry_points.txt
mandrel.egg-info/requires.txt
mandrel.egg-info/top_level.txt
mandrel/config/__init__.py
mandrel/config/core.py
mandrel/config/helpers.py
mandrel/test/__init__.py
mandrel/test/integration_test.py
mandrel/test/runner_test.py
mandrel/test/utils.py
mandrel/test/bootstrap/__init__.py
mandrel/test/bootstrap/bootstrap_file_test.py
mandrel/test/bootstrap/logging_test.py
mandrel/test/bootstrap/search_path_behavior_test.py
mandrel/test/config/__init__.py
mandrel/test/config/configuration_class_test.py
mandrel/test/config/loader_functionality_test.py
mandrel/test/config/loader_helpers_test.py
mandrel/test/config/logger_helpers_test.py
mandrel/test/config/public_interface_test.py
mandrel/test/config/yaml_loader_test.py
mandrel/test/util/__init__.py
mandrel/test/util/file_finder_test.py
mandrel/test/util/fqn_test.py
mandrel/test/util/loaders_test.py
mandrel/test/util/transforming_list_test.py