Metadata-Version: 1.1
Name: mandrel
Version: 1.0.0
Summary: Provides bootstrapping for sane configuration management
Home-page: https://github.com/ethanrowe/python-mandrel
Author: Ethan Rowe
Author-email: ethan@the-rowes.com
License: MIT
Keywords: bootstrap configuration setup
Platform: UNKNOWN
Classifier: Intended Audience :: Developers
Classifier: Intended Audience :: System Administrators
Classifier: License :: OSI Approved :: MIT License
Classifier: Operating System :: OS Independent
Classifier: Programming Language :: Python :: 2.6
Classifier: Programming Language :: Python :: 2.7
Classifier: Topic :: Utilities
